{"basics":{"name":"Tom Fischer","label":"PhD Candidate","image":"","email":"fischertom@outlook.com","phone":"(+49) 1578 9655134","url":"https://fischer-tom.github.io/","summary":"Second Year PhD student in the CVMP Lab at the University of Technology Nuremberg. I am working in Computer Vision with a focus on object representation learning for pose estimation and incremental learning.","location":{"address":"Judengasse 10","postalCode":"90403","city":"Nuremberg","countryCode":"DE","region":"Bavaria"},"profiles":[{"network":"Twitter","username":"AlbertEinstein","url":"https://twitter.com/AlbertEinstein"}]},"work":[{"name":"University of Technology Nuremberg","position":"PhD Candidate","url":"https://www.cvmp-lab.org/","startDate":"2023-10-01","endDate":"","summary":"Teaching at Palmer Physical Laboratory (now 302 Frist Campus Center). While not a professor at Princeton, I associated with the physics professors and continued to give lectures on campus.","highlights":["Incremental Learning","Object Pose Estimation","Detection"]}],"education":[{"institution":"University of Technology Nuremberg","location":"Nuremberg, Germany","url":"https://www.cvmp-lab.org/","area":"Computer Vision","studyType":"PhD Candidate","startDate":"2025-04-01","endDate":"","score":"","courses":[]},{"institution":"Saarland University","location":"Saarbrücken, Germany","url":"https://www.cvmp-lab.org/","area":"Computer Vision","studyType":"PhD Candidate","startDate":"2023-10-01","endDate":"2025-04-01","score":"","courses":[]},{"institution":"Saarland University","location":"Saarbrücken, Germany","url":"https://saarland-informatics-campus.de/en/","area":"Computer Science","studyType":"Master of Science","startDate":"2020-10-15","endDate":"2023-05-01","score":"","courses":[]},{"institution":"Saarland University","location":"Saarbrücken, Germany","url":"https://saarland-informatics-campus.de/en/","area":"Cybersecurity","studyType":"Bachelor of Science","startDate":"2016-10-15","endDate":"2020-10-15","score":"","courses":[]}],"skills":[{"name":"Software Skills","level":"Master","icon":"fa-solid fa-hashtag","keywords":["Python","CUDA","Linux","Docker"]},{"name":"Frameworks","level":"Master","icon":"fa-solid fa-hashtag","keywords":["PyTorch","PyTorch3D"]}],"languages":[{"language":"German","fluency":"Native speaker","icon":""},{"language":"English","fluency":"Fluent","icon":""},{"language":"Spanish","fluency":"Conversationally fluent","icon":""}],"interests":[{"name":"Primary","icon":"fa-solid fa-tag","keywords":["3D Computer Vision","Representation Learning","Object Pose Estimation","Incremental Learning"]},{"name":"Secondary","icon":"fa-solid fa-tag","keywords":["3D Reconstruction","Image and video synthesis","Computer Graphics","Self-supervised Learning"]}]}